[{"grupo":"-","fecha":"2025-07-29","cantidad":57},{"grupo":"AMBIENTALES","fecha":"2025-07-29","cantidad":5},{"grupo":"CONSTRUCCION","fecha":"2025-07-29","cantidad":47},{"grupo":"CONSULTORIA","fecha":"2025-07-29","cantidad":11},{"grupo":"GENERALES","fecha":"2025-07-29","cantidad":3},{"grupo":"MAQUINARIAS","fecha":"2025-07-29","cantidad":9},{"grupo":"MATERIALES","fecha":"2025-07-29","cantidad":163},{"grupo":"SOCIALES","fecha":"2025-07-29","cantidad":26},{"grupo":"-","fecha":"2025-07-30","cantidad":59},{"grupo":"AMBIENTALES","fecha":"2025-07-30","cantidad":3},{"grupo":"CONSTRUCCION","fecha":"2025-07-30","cantidad":50},{"grupo":"CONSULTORIA","fecha":"2025-07-30","cantidad":10},{"grupo":"GENERALES","fecha":"2025-07-30","cantidad":8},{"grupo":"MAQUINARIAS","fecha":"2025-07-30","cantidad":19},{"grupo":"MATERIALES","fecha":"2025-07-30","cantidad":188},{"grupo":"SOCIALES","fecha":"2025-07-30","cantidad":23},{"grupo":"-","fecha":"2025-07-31","cantidad":76},{"grupo":"AMBIENTALES","fecha":"2025-07-31","cantidad":6},{"grupo":"CONSTRUCCION","fecha":"2025-07-31","cantidad":53},{"grupo":"CONSULTORIA","fecha":"2025-07-31","cantidad":13},{"grupo":"GENERALES","fecha":"2025-07-31","cantidad":7},{"grupo":"MAQUINARIAS","fecha":"2025-07-31","cantidad":23},{"grupo":"MATERIALES","fecha":"2025-07-31","cantidad":276},{"grupo":"SOCIALES","fecha":"2025-07-31","cantidad":29},{"grupo":"-","fecha":"2025-08-01","cantidad":41},{"grupo":"AMBIENTALES","fecha":"2025-08-01","cantidad":3},{"grupo":"CONSTRUCCION","fecha":"2025-08-01","cantidad":37},{"grupo":"CONSULTORIA","fecha":"2025-08-01","cantidad":10},{"grupo":"GENERALES","fecha":"2025-08-01","cantidad":20},{"grupo":"MAQUINARIAS","fecha":"2025-08-01","cantidad":12},{"grupo":"MATERIALES","fecha":"2025-08-01","cantidad":164},{"grupo":"SOCIALES","fecha":"2025-08-01","cantidad":18},{"grupo":"MATERIALES","fecha":"2025-08-02","cantidad":1},{"grupo":"-","fecha":"2025-08-03","cantidad":4},{"grupo":"MATERIALES","fecha":"2025-08-03","cantidad":1},{"grupo":"-","fecha":"2025-08-04","cantidad":33},{"grupo":"AMBIENTALES","fecha":"2025-08-04","cantidad":1},{"grupo":"CONSTRUCCION","fecha":"2025-08-04","cantidad":17},{"grupo":"CONSULTORIA","fecha":"2025-08-04","cantidad":1},{"grupo":"GENERALES","fecha":"2025-08-04","cantidad":1},{"grupo":"MAQUINARIAS","fecha":"2025-08-04","cantidad":9},{"grupo":"MATERIALES","fecha":"2025-08-04","cantidad":64},{"grupo":"SOCIALES","fecha":"2025-08-04","cantidad":2},{"grupo":"-","fecha":"2025-08-05","cantidad":59},{"grupo":"AMBIENTALES","fecha":"2025-08-05","cantidad":3},{"grupo":"CONSTRUCCION","fecha":"2025-08-05","cantidad":27},{"grupo":"CONSULTORIA","fecha":"2025-08-05","cantidad":5},{"grupo":"GENERALES","fecha":"2025-08-05","cantidad":2},{"grupo":"MAQUINARIAS","fecha":"2025-08-05","cantidad":15},{"grupo":"MATERIALES","fecha":"2025-08-05","cantidad":120},{"grupo":"SOCIALES","fecha":"2025-08-05","cantidad":14},{"grupo":"-","fecha":"2025-08-06","cantidad":1},{"grupo":"MATERIALES","fecha":"2025-08-06","cantidad":2},{"grupo":"-","fecha":"2025-08-07","cantidad":2},{"grupo":"CONSULTORIA","fecha":"2025-08-07","cantidad":1},{"grupo":"MATERIALES","fecha":"2025-08-07","cantidad":4},{"grupo":"-","fecha":"2025-08-08","cantidad":51},{"grupo":"AMBIENTALES","fecha":"2025-08-08","cantidad":3},{"grupo":"CONSTRUCCION","fecha":"2025-08-08","cantidad":38},{"grupo":"CONSULTORIA","fecha":"2025-08-08","cantidad":7},{"grupo":"FINANCIEROS","fecha":"2025-08-08","cantidad":1},{"grupo":"GENERALES","fecha":"2025-08-08","cantidad":5},{"grupo":"MAQUINARIAS","fecha":"2025-08-08","cantidad":11},{"grupo":"MATERIALES","fecha":"2025-08-08","cantidad":95},{"grupo":"SOCIALES","fecha":"2025-08-08","cantidad":10},{"grupo":"-","fecha":"2025-08-09","cantidad":1},{"grupo":"MATERIALES","fecha":"2025-08-09","cantidad":8},{"grupo":"-","fecha":"2025-08-10","cantidad":3},{"grupo":"CONSTRUCCION","fecha":"2025-08-10","cantidad":3},{"grupo":"MATERIALES","fecha":"2025-08-10","cantidad":1},{"grupo":"-","fecha":"2025-08-11","cantidad":23},{"grupo":"AMBIENTALES","fecha":"2025-08-11","cantidad":1},{"grupo":"CONSTRUCCION","fecha":"2025-08-11","cantidad":20},{"grupo":"CONSULTORIA","fecha":"2025-08-11","cantidad":2},{"grupo":"GENERALES","fecha":"2025-08-11","cantidad":1},{"grupo":"MAQUINARIAS","fecha":"2025-08-11","cantidad":7},{"grupo":"MATERIALES","fecha":"2025-08-11","cantidad":80},{"grupo":"SOCIALES","fecha":"2025-08-11","cantidad":11},{"grupo":"-","fecha":"2025-08-12","cantidad":38},{"grupo":"AMBIENTALES","fecha":"2025-08-12","cantidad":4},{"grupo":"CONSTRUCCION","fecha":"2025-08-12","cantidad":39},{"grupo":"CONSULTORIA","fecha":"2025-08-12","cantidad":5},{"grupo":"GENERALES","fecha":"2025-08-12","cantidad":1},{"grupo":"MAQUINARIAS","fecha":"2025-08-12","cantidad":11},{"grupo":"MATERIALES","fecha":"2025-08-12","cantidad":115},{"grupo":"SOCIALES","fecha":"2025-08-12","cantidad":6},{"grupo":"-","fecha":"2025-08-13","cantidad":52},{"grupo":"AMBIENTALES","fecha":"2025-08-13","cantidad":3},{"grupo":"CONSTRUCCION","fecha":"2025-08-13","cantidad":20},{"grupo":"CONSULTORIA","fecha":"2025-08-13","cantidad":2},{"grupo":"GENERALES","fecha":"2025-08-13","cantidad":3},{"grupo":"MAQUINARIAS","fecha":"2025-08-13","cantidad":12},{"grupo":"MATERIALES","fecha":"2025-08-13","cantidad":102},{"grupo":"SOCIALES","fecha":"2025-08-13","cantidad":11}]